{
  "generated_at": "2025-08-18 09:05:08",
  "backtest_period": "12 days",
  "verified_symbols": [
    {
      "symbol": "062040",
      "name": "산일전기",
      "strategy": "scalping",
      "return": 8.74,
      "win_rate": 0.833,
      "sharpe_ratio": 6.324,
      "max_drawdown": -0.003,
      "total_trades": 6,
      "priority": 1,
      "last_updated": "2025-08-18 09:05:08"
    },
    {
      "symbol": "278470",
      "name": "에이피알",
      "strategy": "momentum",
      "return": 1.2,
      "win_rate": 0.429,
      "sharpe_ratio": 0.346,
      "max_drawdown": -0.093,
      "total_trades": 7,
      "priority": 2,
      "last_updated": "2025-08-18 09:05:08"
    }
  ],
  "summary": {
    "total_symbols": 2,
    "avg_return": 4.97,
    "best_symbol": "062040",
    "best_return": 8.74
  }
}